evva_airkey/Session.py
evva_airkey/__init__.py
evva_airkey/api.py
evva_airkey/fapi.py
evva_airkey-0.0.5.dist-info/LICENSE
evva_airkey-0.0.5.dist-info/METADATA
evva_airkey-0.0.5.dist-info/WHEEL
evva_airkey-0.0.5.dist-info/top_level.txt
evva_airkey-0.0.5.dist-info/RECORD
