Metadata-Version: 2.1
Name: evva_airkey
Version: 0.0.5
Summary: Communication module for EVVA Airkey cloud integration
Author: Giampaolo Eusebi
Author-email: giampaolo.eusebi@gmail.com
License: GNU LGPL 3.0
Project-URL: Source, https://gitlab.com/geusebi/evva_airkey
Classifier: Development Status :: 4 - Beta
Classifier: Intended Audience :: Developers
Classifier: Intended Audience :: System Administrators
Classifier: License :: OSI Approved
Classifier: License :: OSI Approved :: GNU Lesser General Public License v3 (LGPLv3)
Classifier: Operating System :: OS Independent
Classifier: Programming Language :: Python
Classifier: Programming Language :: Python :: 3
Classifier: Programming Language :: Python :: 3.6
Classifier: Programming Language :: Python :: 3.7
Classifier: Programming Language :: Python :: 3.8
Classifier: Programming Language :: Python :: 3.9
Classifier: Topic :: Utilities
Requires-Python: >=3.6
License-File: LICENSE
Requires-Dist: requests
